MANIFEST.in
README.rst
requirements-dev.txt
requirements.txt
setup.py
pyugrid/__init__.py
pyugrid/read_netcdf.py
pyugrid/ugrid.py
pyugrid/ugrid_wx.py
pyugrid/util.py
pyugrid/uvar.py
pyugrid.egg-info/PKG-INFO
pyugrid.egg-info/SOURCES.txt
pyugrid.egg-info/dependency_links.txt
pyugrid.egg-info/entry_points.txt
pyugrid.egg-info/requires.txt
pyugrid.egg-info/top_level.txt
pyugrid/grid_io/__init__.py
pyugrid/grid_io/utils.py
test/test_add_data.py
test/test_find_nodes.py
test/test_find_uvar.py
test/test_flexible_mesh.py
test/test_grid_manipulation.py
test/test_io_util.py
test/test_locate_faces.py
test/test_point_in_triangle.py
test/test_read.py
test/test_save_as_netcdf.py
test/test_ugrid.py
test/test_util.py
test/test_uvar.py
test/test_write_read.py
test/utilities.py
test/write_nc_test_files.py
test/files/ElevenPoints_UGRIDv0.9.nc
test/files/junk.nc
test/files/no_stand_name_long.nc
test/files/quad_and_triangle.nc