Metadata-Version: 1.1
Name: pyugrid
Version: 0.3.1
Summary: A package for working with triangular unstructured grids, and the data on them
Home-page: https://github.com/pyugrid/pyugrid
Author: Chris Barker, Chris Calloway, Rich Signell
Author-email: Chris.Barker@noaa.gov
License: BSD
Keywords: unstructured numpy models
Platform: UNKNOWN
Classifier: Development Status :: 3 - Alpha
Classifier: Topic :: Utilities
Classifier: License :: OSI Approved :: BSD License
Classifier: Programming Language :: Python
Classifier: Programming Language :: Python :: 2
Classifier: Programming Language :: Python :: 2.7
Classifier: Programming Language :: Python :: 3
Classifier: Programming Language :: Python :: 3.4
Classifier: Programming Language :: Python :: 3.5
